{
  "resourceType": "StructureDefinition",
  "id": "who-fp-careplan-exit-contraceptive-method",
  "url": "http://hl7.org/fhir/dbcg/fp-cds/ImplementationGuide/fp-cds/StructureDefinition/who-fp-careplan-exit-contraceptive-method",
  "name": "who-fp-careplan-exit-contraceptive-method",
  "title": "who-fp-careplan-exit-contraceptive-method",
  "status": "draft",
  "experimental": false,
  "description": "who-fp-careplan-exit-contraceptive-method",
  "fhirVersion": "4.0.0",
  "kind": "resource",
  "abstract": false,
  "type": "CarePlan",
  "baseDefinition": "http://hl7.org/fhir/StructureDefinition/CarePlan",
  "derivation": "constraint",
  "differential": {
    "element": [
      {
        "id": "CarePlan",
        "path": "CarePlan",
        "mustSupport": false
      },
      {
        "id": "CarePlan.activity.detail.code",
        "path": "CarePlan.activity.detail.code",
        "min": 0,
        "max": "*",
        "type": [
          {
            "code": "CodeableConcept"
          }
        ],
        "mustSupport": true
      }
    ]
  }
}