{
  "resourceType": "ValueSet",
  "id": "breast-cancer-values",
  "url": "http://hl7.org/fhir/dbcg/fp-cds/ImplementationGuide/fp-cds/ValueSet/breast-cancer-values",
  "name": "breast-cancer-values",
  "title": "Breast cancer values",
  "status": "draft",
  "experimental": false,
  "description": "Codes representing possible values for the Breast cancer element",
  "immutable": true,
  "compose": {
    "include": [
      {
        "system": "http://hl7.org/fhir/sid/icd-10",
        "concept": [
          {
            "code": "N64.9",
            "display": "Current"
          },
          {
            "code": "z85.3 plus 5 years",
            "display": "Past, no evidence of disease for at least 5 years"
          }
        ]
      }
    ]
  }
}